setup.py
livebridge_liveblog/__init__.py
livebridge_liveblog/common.py
livebridge_liveblog/converters.py
livebridge_liveblog/post.py
livebridge_liveblog/source.py
livebridge_liveblog/target.py
livebridge_liveblog.egg-info/PKG-INFO
livebridge_liveblog.egg-info/SOURCES.txt
livebridge_liveblog.egg-info/dependency_links.txt
livebridge_liveblog.egg-info/not-zip-safe
livebridge_liveblog.egg-info/requires.txt
livebridge_liveblog.egg-info/top_level.txt