Metadata-Version: 1.1
Name: livebridge-liveblog
Version: 0.3.0
Summary: Liveblog plugin for Livebridge.
Home-page: https://github.com/dpa-newslab/livebridge-scribblelive
Author: Martin Borho
Author-email: martin@borho.net
License: Apache Software License (http://www.apache.org/licenses/LICENSE-2.0)
Keywords: liveticker,scribblelive,syndication
Platform: UNKNOWN
Classifier: Programming Language :: Python :: 3.5
Classifier: Topic :: Communications
Classifier: Development Status :: 4 - Beta
Classifier: License :: OSI Approved :: Apache Software License
Classifier: Intended Audience :: Other Audience
Classifier: Operating System :: POSIX :: Linux
Classifier: Environment :: Console
Classifier: Environment :: Plugins
